Lab93DatabaseSystem/__init__.py
Lab93DatabaseSystem/submodules/__init__.py
Lab93DatabaseSystem/submodules/DatabaseAPI/SQLite3.py
Lab93DatabaseSystem/submodules/DatabaseAPI/Shelve.py
Lab93DatabaseSystem/submodules/DatabaseAPI/__init__.py
Lab93DatabaseSystem-0.0.6.dist-info/METADATA
Lab93DatabaseSystem-0.0.6.dist-info/WHEEL
Lab93DatabaseSystem-0.0.6.dist-info/top_level.txt
Lab93DatabaseSystem-0.0.6.dist-info/RECORD
