Metadata-Version: 2.1
Name: Lab93DatabaseSystem
Version: 0.0.6
Summary: An API for object persistence scriptability.
Author-email: Hunter Dale <hunter@guyyatsu.me>
Project-URL: Homepage, https://github.com/guyyatsu/Lab93-DatabaseSystem
Project-URL: Bug Tracker, https://github.com/guyyatsu/Lab93-DatabaseSystem/issues
Classifier: Programming Language :: Python :: 3
Classifier: License :: OSI Approved :: MIT License
Classifier: Operating System :: OS Independent
Requires-Python: >=3.10
